{
    "eventos":[
        {
            "id":1,
            "evento":"Evento lo alternativo 1",
            "fecha":"22-12-2022",
            "precio":50,
            "direccion":"",
            "provincia":"",
            "localidad":"",
            "codigo_postal":"",
            "online":true,
            "organizador":"LöAlternativo",
            "descripcion":"Lorem ipsum dolor sit amet, consectetur adipiscing elit, sed do eiusmod tempor incididunt ut labore et dolore magna aliqua. Ut enim ad minim veniam, quis nostrud exercitation ullamco laboris nisi ut aliquip ex ea commodo consequat.",
            "imagen":"./../../../../assets/images/eventosEsoterismo/imagen_1.jpg",
            "telefono":"612345678",
            "email":"loalternativo@email.com",
            "web":"https://www.loalternativo.es",
            "twitter":"@loalternativo",
            "facebook":"loalternativo",
            "instagram":"loalternativo",
            "you_tube":"loalternativo youtube"
        },
        {
            "id":2,
            "evento":"Evento lo alternativo 2",
            "fecha":"22-12-2022",
            "precio":0,
            "direccion":"",
            "provincia":"",
            "localidad":"",
            "codigo_postal":"",
            "online":true,
            "organizador":"LöAlternativo",
            "descripcion":"Lorem ipsum dolor sit amet, consectetur adipiscing elit, sed do eiusmod tempor incididunt ut labore et dolore magna aliqua. Ut enim ad minim veniam, quis nostrud exercitation ullamco laboris nisi ut aliquip ex ea commodo consequat.",
            "imagen":"./../../../../assets/images/eventosEsoterismo/imagen_1.jpg",
            "telefono":"612345678",
            "email":"loalternativo@email.com",
            "web":"https://www.loalternativo.es",
            "twitter":"@loalternativo",
            "facebook":"loalternativo",
            "instagram":"loalternativo",
            "you_tube":"loalternativo youtube"
        },
        {
            "id":3,
            "evento":"Evento lo alternativo 3",
            "fecha":"22-12-2022",
            "precio":100,
            "direccion":"",
            "provincia":"",
            "localidad":"",
            "codigo_postal":"",
            "online":true,
            "organizador":"LöAlternativo",
            "descripcion":"Lorem ipsum dolor sit amet, consectetur adipiscing elit, sed do eiusmod tempor incididunt ut labore et dolore magna aliqua. Ut enim ad minim veniam, quis nostrud exercitation ullamco laboris nisi ut aliquip ex ea commodo consequat.",
            "imagen":"./../../../../assets/images/eventosEsoterismo/imagen_1.jpg",
            "telefono":"612345678",
            "email":"loalternativo@email.com",
            "web":"https://www.loalternativo.es",
            "twitter":"@loalternativo",
            "facebook":"loalternativo",
            "instagram":"loalternativo",
            "you_tube":"loalternativo youtube"
        },
        {
            "id":4,
            "evento":"Evento lo alternativo 4",
            "fecha":"22-12-2022",
            "precio":0,
            "direccion":"",
            "provincia":"",
            "localidad":"",
            "codigo_postal":"",
            "online":true,
            "organizador":"LöAlternativo",
            "descripcion":"Lorem ipsum dolor sit amet, consectetur adipiscing elit, sed do eiusmod tempor incididunt ut labore et dolore magna aliqua. Ut enim ad minim veniam, quis nostrud exercitation ullamco laboris nisi ut aliquip ex ea commodo consequat.",
            "imagen":"./../../../../assets/images/eventosEsoterismo/imagen_1.jpg",
            "telefono":"612345678",
            "email":"loalternativo@email.com",
            "web":"https://www.loalternativo.es",
            "twitter":"@loalternativo",
            "facebook":"loalternativo",
            "instagram":"loalternativo",
            "you_tube":"loalternativo youtube"
        },
        {
            "id":0,
            "evento":"Revista",
            "fecha":"22-12-2022",
            "precio":0,
            "direccion":"",
            "provincia":"",
            "localidad":"",
            "codigo_postal":"",
            "online":true,
            "organizador":"LöAlternativo",
            "descripcion":"Revista semanal LöAlternativo",
            "imagen":"./../../../../assets/images/eventosEsoterismo/imagen_1.jpg",
            "telefono":"612345678",
            "email":"loalternativo@email.com",
            "web":"https://www.loalternativo.es",
            "twitter":"@loalternativo",
            "facebook":"loalternativo",
            "instagram":"loalternativo",
            "you_tube":"loalternativo youtube"
        }

    ]
}